trilite.cpython-312-x86_64-linux-gnu.so
trilite-0.4.1.dist-info/METADATA
trilite-0.4.1.dist-info/WHEEL
trilite-0.4.1.dist-info/top_level.txt
trilite-0.4.1.dist-info/RECORD
