Metadata-Version: 2.1
Name: trilite
Version: 0.4.1
Summary: Python binding for the TriLite library
Author: MeshLite
Author-email: meshlite.developers@gmail.com
Requires-Dist: numpy
Requires-Dist: pybind11
